ml4h_latentverse/__init__.py
ml4h_latentverse/utils.py
ml4h_latentverse/__pycache__/__init__.cpython-39.pyc
ml4h_latentverse/__pycache__/utils.cpython-39.pyc
ml4h_latentverse/tests/__init__.py
ml4h_latentverse/tests/clustering.py
ml4h_latentverse/tests/disentanglement.py
ml4h_latentverse/tests/expressiveness.py
ml4h_latentverse/tests/probing.py
ml4h_latentverse/tests/robustness.py
ml4h_latentverse/tests/__pycache__/__init__.cpython-39.pyc
ml4h_latentverse/tests/__pycache__/clustering.cpython-39.pyc
ml4h_latentverse/tests/__pycache__/disentanglement.cpython-39.pyc
ml4h_latentverse/tests/__pycache__/expressiveness.cpython-39.pyc
ml4h_latentverse/tests/__pycache__/probing.cpython-39.pyc
ml4h_latentverse/tests/__pycache__/robustness.cpython-39.pyc
ml4h_latentverse-0.1.2.dist-info/licenses/LICENSE
tests/__init__.py
tests/test.py
tests/test_metrics.py
ml4h_latentverse-0.1.2.dist-info/METADATA
ml4h_latentverse-0.1.2.dist-info/WHEEL
ml4h_latentverse-0.1.2.dist-info/top_level.txt
ml4h_latentverse-0.1.2.dist-info/RECORD
