Metadata-Version: 2.4
Name: ml4h-latentverse
Version: 0.1.2
Summary: Evaluation library for latent representations
Author: Yoanna Turura
Author-email: Yoanna Turura <yturura@broadinstitute.org>
Requires-Python: >=3.7
License-File: LICENSE
Requires-Dist: numpy
Requires-Dist: scipy
Requires-Dist: pandas
Requires-Dist: scikit-learn
Requires-Dist: matplotlib
Requires-Dist: seaborn
Requires-Dist: twine
Requires-Dist: wheel
Requires-Dist: build
Dynamic: author
Dynamic: license-file
Dynamic: requires-python
